fpe/__init__.py
fpe/fpe.py
fpe_library-0.2.0.dist-info/LICENSE
fpe_library-0.2.0.dist-info/METADATA
fpe_library-0.2.0.dist-info/WHEEL
fpe_library-0.2.0.dist-info/top_level.txt
fpe_library-0.2.0.dist-info/RECORD
