Metadata-Version: 2.1
Name: fpe-library
Version: 0.2.0
Summary: Feature Probability Estimation-based Feature Selection Method
Author: Nehal Varma
Author-email: nehalvarma85@gmail.com
Classifier: Programming Language :: Python :: 3
Classifier: License :: OSI Approved :: MIT License
Classifier: Operating System :: OS Independent
Requires-Python: >=3.6
License-File: LICENSE
Requires-Dist: pandas >=1.0.0
Requires-Dist: numpy >=1.18.0
Requires-Dist: scikit-learn >=0.22.0
